Metadata-Version: 1.0
Name: faker-rainbow-collection
Version: 0.1.1
Summary: A collection of provides for the Faker data generator.
Home-page: UNKNOWN
Author: Daniil Trishkin
Author-email: UNKNOWN
License: MIT
Platform: UNKNOWN
